mktheapidocs/__init__.py
mktheapidocs/_version.py
mktheapidocs/mkapi.py
mktheapidocs/plugin.py
mktheapidocs-0.3.1.dist-info/LICENSE
mktheapidocs-0.3.1.dist-info/METADATA
mktheapidocs-0.3.1.dist-info/WHEEL
mktheapidocs-0.3.1.dist-info/entry_points.txt
mktheapidocs-0.3.1.dist-info/top_level.txt
mktheapidocs-0.3.1.dist-info/RECORD
