Metadata-Version: 2.1
Name: mktheapidocs
Version: 0.3.1
Summary: Generate markdown API documentation from Numpydoc docstrings.
Home-page: https://github.com/greenape/mktheapidocs
Author: Jonathan Gray
Author-email: jonathan.gray@nanosheep.net
License: 
Keywords: mkdocs documentation markdown
Platform: MacOS X
Platform: Linux
Classifier: Development Status :: 3 - Alpha
Classifier: Intended Audience :: Developers
Classifier: License :: OSI Approved :: MIT License
Classifier: Programming Language :: Python :: 3.6
Classifier: Natural Language :: English
Classifier: Operating System :: MacOS :: MacOS X
Classifier: Operating System :: POSIX
Classifier: Operating System :: POSIX :: Linux
License-File: LICENSE
Requires-Dist: numpydoc
Requires-Dist: black
Requires-Dist: click
Provides-Extra: plugin
Requires-Dist: mkdocs (>=1.2) ; extra == 'plugin'
